cleary/__init__.py
cleary/__main__.py
cleary-0.1.1.dist-info/METADATA
cleary-0.1.1.dist-info/WHEEL
cleary-0.1.1.dist-info/entry_points.txt
cleary-0.1.1.dist-info/top_level.txt
cleary-0.1.1.dist-info/RECORD
