Metadata-Version: 2.4
Name: cleary
Version: 0.1.1
Summary: Ultimate cross-platform console clearer
Author: TroubleGy
Requires-Python: >=3.6
Dynamic: author
Dynamic: description
Dynamic: description-content-type
Dynamic: requires-python
Dynamic: summary
